moviz-0.4.3.dist-info/licenses/LICENSE
mviz/__init__.py
mviz/cli.py
mviz/main.py
mviz/configs/robot.py
mviz/ice_tools/__init__.py
mviz/ice_tools/test_pub.py
mviz/ice_tools/test_quat_pub.py
mviz/ice_tools/test_quat_sub.py
mviz/ice_tools/test_sub.py
mviz/ice_tools/msgs/__init__.py
mviz/ice_tools/msgs/geometry.py
mviz/ice_tools/msgs/imu.py
mviz/ice_tools/msgs/kpose.py
mviz/ice_tools/msgs/odometry.py
mviz/ice_tools/msgs/pointcloud2.py
mviz/ice_tools/msgs/quat_g1.py
mviz/ice_tools/msgs/quaternion.py
mviz/ice_tools/msgs/state_g1.py
mviz/ice_tools/utils/__init__.py
mviz/ice_tools/utils/cli_echo.py
mviz/ice_tools/utils/cli_hz.py
mviz/ice_tools/utils/cli_info.py
mviz/ice_tools/utils/cli_play.py
mviz/ice_tools/utils/cli_record.py
mviz/ice_tools/utils/subscription.py
mviz/plugins/__init__.py
mviz/plugins/pointcloud/__init__.py
mviz/robots/smplh/female/model.npz
mviz/robots/smplh/male/model.npz
mviz/robots/smplh/neutral/model.npz
mviz/robots/unitree/g1/README.md
mviz/robots/unitree/g1/g1_23dof.urdf
mviz/robots/unitree/g1/g1_23dof.xml
mviz/robots/unitree/g1/g1_23dof_mode_10.urdf
mviz/robots/unitree/g1/g1_23dof_rev_1_0.urdf
mviz/robots/unitree/g1/g1_23dof_rev_1_0.xml
mviz/robots/unitree/g1/g1_29dof.urdf
mviz/robots/unitree/g1/g1_29dof.xml
mviz/robots/unitree/g1/g1_29dof_lock_waist.urdf
mviz/robots/unitree/g1/g1_29dof_lock_waist.xml
mviz/robots/unitree/g1/g1_29dof_lock_waist_rev_1_0.urdf
mviz/robots/unitree/g1/g1_29dof_lock_waist_rev_1_0.xml
mviz/robots/unitree/g1/g1_29dof_lock_waist_with_hand_rev_1_0.urdf
mviz/robots/unitree/g1/g1_29dof_lock_waist_with_hand_rev_1_0.xml
mviz/robots/unitree/g1/g1_29dof_mode_11.urdf
mviz/robots/unitree/g1/g1_29dof_mode_12.urdf
mviz/robots/unitree/g1/g1_29dof_mode_13.urdf
mviz/robots/unitree/g1/g1_29dof_mode_14.urdf
mviz/robots/unitree/g1/g1_29dof_mode_15.urdf
mviz/robots/unitree/g1/g1_29dof_mode_16.urdf
mviz/robots/unitree/g1/g1_29dof_rev_1_0.urdf
mviz/robots/unitree/g1/g1_29dof_rev_1_0.xml
mviz/robots/unitree/g1/g1_29dof_rev_1_0_with_inspire_hand_DFQ.urdf
moviz-0.4.3.dist-info/METADATA
moviz-0.4.3.dist-info/WHEEL
moviz-0.4.3.dist-info/entry_points.txt
moviz-0.4.3.dist-info/top_level.txt
moviz-0.4.3.dist-info/RECORD
