Metadata-Version: 2.4
Name: moviz
Version: 0.4.3
Summary: Motion visualization tool for humanoid robots
Author-email: a <a@a.com>
License-Expression: MIT
Keywords: robotics,visualization,motion
Classifier: Development Status :: 3 - Alpha
Classifier: Intended Audience :: Science/Research
Classifier: Programming Language :: Python :: 3
Classifier: Programming Language :: Python :: 3.11
Classifier: Programming Language :: Python :: 3.12
Classifier: Operating System :: OS Independent
Classifier: Topic :: Scientific/Engineering :: Visualization
Requires-Python: >=3.11
License-File: LICENSE
Requires-Dist: numpy
Requires-Dist: trimesh
Requires-Dist: viser
Requires-Dist: pyyaml
Requires-Dist: termcolor
Requires-Dist: iceoryx2
Requires-Dist: ezc3d
Requires-Dist: tqdm
Requires-Dist: yourdfpy
Dynamic: license-file
